pro_video_ferramenas/__init__.py
pro_video_ferramenas/camera.py
pro_video_ferramenas/video.py
ferramentas_pro_camera-1.0.dist-info/METADATA
ferramentas_pro_camera-1.0.dist-info/WHEEL
ferramentas_pro_camera-1.0.dist-info/license.txt
ferramentas_pro_camera-1.0.dist-info/top_level.txt
ferramentas_pro_camera-1.0.dist-info/RECORD
