Metadata-Version: 2.1
Name: ferramentas_pro_camera
Version: 1.0
Summary: Este pacote irá fornecer ferramentas de processamento de video
Author: Diogo Jesus
Author-email: diogojesus.nascimento@outlook.com
Keywords: Camera,Video,Processamento
License-File: license.txt
